{"namedChunkGroups":{"polyfill":{"name":"polyfill","assets":[{"name":"webpack-runtime-7fcee28f1d2900e3b732.js","size":4366},{"name":"polyfill-87ef2ad0d8ccb1217640.js","size":82641}],"filteredAssets":0,"assetsSize":87007,"filteredAuxiliaryAssets":2,"auxiliaryAssetsSize":218937},"app":{"name":"app","assets":[{"name":"webpack-runtime-7fcee28f1d2900e3b732.js","size":4366},{"name":"framework-0964177974740cdf2ed8.js","size":128888},{"name":"app-615a8fc48a0c1e350630.js","size":67456}],"filteredAssets":0,"assetsSize":200710,"filteredAuxiliaryAssets":3,"auxiliaryAssetsSize":654116},"component---src-pages-404-js":{"name":"component---src-pages-404-js","assets":[{"name":"component---src-pages-404-js-3b6698ad7bb81213937c.js","size":769}],"filteredAssets":0,"assetsSize":769,"filteredAuxiliaryAssets":1,"auxiliaryAssetsSize":1873},"component---src-pages-index-js":{"name":"component---src-pages-index-js","assets":[{"name":"styles.e3e52e3a96d430cc550c.css","size":8852},{"name":"component---src-pages-index-js-dfb9797f3a395700f6c9.js","size":41981}],"filteredAssets":0,"assetsSize":50833,"filteredAuxiliaryAssets":22,"auxiliaryAssetsSize":1237494},"component---src-pages-privacypolicy-js":{"name":"component---src-pages-privacypolicy-js","assets":[{"name":"component---src-pages-privacypolicy-js-ad167469e7fab666b5d4.js","size":12870}],"filteredAssets":0,"assetsSize":12870,"filteredAuxiliaryAssets":1,"auxiliaryAssetsSize":16525}},"assetsByChunkName":{"polyfill":["webpack-runtime-7fcee28f1d2900e3b732.js","polyfill-87ef2ad0d8ccb1217640.js"],"app":["webpack-runtime-7fcee28f1d2900e3b732.js","framework-0964177974740cdf2ed8.js","app-615a8fc48a0c1e350630.js"],"component---src-pages-404-js":["component---src-pages-404-js-3b6698ad7bb81213937c.js"],"component---src-pages-index-js":["styles.e3e52e3a96d430cc550c.css","component---src-pages-index-js-dfb9797f3a395700f6c9.js"],"component---src-pages-privacypolicy-js":["component---src-pages-privacypolicy-js-ad167469e7fab666b5d4.js"]},"childAssetsByChunkName":{}}